<?xml version="1.0" encoding="UTF-8"?>
<!DOCTYPE hibernate-mapping PUBLIC
    "-//Hibernate/Hibernate Mapping DTD 3.0//EN"
    "http://hibernate.org/dtd/hibernate-mapping-3.0.dtd">
 <hibernate-mapping default-access="field"
 	default-cascade="save-update">
 	<class name="model.Telephone">
 		<id column="idUser" name="id">
 			<generator class="foreign" >
 			<param name="property">user</param>
 			            </generator>
 		</id>
 		<property name="countryCode" />
 		<property name="areaCode" />
 		<property name="localNumber" />
 		        <one-to-one name="user" constrained="true" class="model.User" />
 	</class>
 </hibernate-mapping>